ekscli/__init__.py
ekscli/bootstrap.py
ekscli/cli.py
ekscli/stack.py
ekscli/utils.py
ekscli/thirdparty/__init__.py
ekscli/thirdparty/click_alias/__init__.py
ekscli-0.1.0rc5.dist-info/METADATA
ekscli-0.1.0rc5.dist-info/RECORD
ekscli-0.1.0rc5.dist-info/WHEEL
ekscli-0.1.0rc5.dist-info/entry_points.txt
ekscli-0.1.0rc5.dist-info/top_level.txt
