Metadata-Version: 2.1
Name: ekscli
Version: 0.1.0rc5
Summary: A simple and flexible commandline tool for AWS EKS management
Home-page: https://github.com/cakab/ekscli
Author: Charles Zhang
Author-email: charles.cakab@gmail.com
License: MIT license
Keywords: ekscli
Platform: UNKNOWN
Classifier: Development Status :: 4 - Beta
Classifier: Intended Audience :: Developers
Classifier: Intended Audience :: System Administrators
Classifier: Natural Language :: English
Classifier: License :: OSI Approved :: MIT License
Classifier: Natural Language :: English
Classifier: Programming Language :: Python :: 2
Classifier: Programming Language :: Python :: 2.7
Classifier: Programming Language :: Python :: 3
Classifier: Programming Language :: Python :: 3.4
Classifier: Programming Language :: Python :: 3.5
Classifier: Programming Language :: Python :: 3.6
Requires-Dist: click (>=6.0)
Requires-Dist: future (>=0.16.0)
Requires-Dist: troposphere (>=2.3.1)
Requires-Dist: awacs (>=0.7.2)
Requires-Dist: boto3 (>=1.7.37)
Requires-Dist: halo (>=0.0.12)
Requires-Dist: kubernetes (>=6.0.0)
Requires-Dist: oyaml (>=0.4)
Requires-Dist: jinja2 (>=2.10)
Requires-Dist: netaddr (>=0.7.19)
Requires-Dist: tabulate (>=0.8.2)
Requires-Dist: ec2-metadata (>=1.6.0)
